tests/__init__.py
tests/test_featuremaps.py
tests/test_main.py
torchconvview/__init__.py
torchconvview/featuremaps.py
torchconvview/pca_view.py
torchconvview/utils.py
torchconvview/view.py
torchconvview-0.2.0.dist-info/LICENSE
torchconvview-0.2.0.dist-info/METADATA
torchconvview-0.2.0.dist-info/WHEEL
torchconvview-0.2.0.dist-info/top_level.txt
torchconvview-0.2.0.dist-info/RECORD
