Metadata-Version: 2.1
Name: torchconvview
Version: 0.2.0
Summary: A library for PyTorch convolution layer visualizations.
Home-page: https://github.com/paulgavrikov/torchconvview
Author: Paul Gavrikov
Author-email: paul.gavrikov@hs-offenburg.de
Classifier: Programming Language :: Python :: 3
Classifier: License :: OSI Approved :: MIT License
Classifier: Operating System :: OS Independent
Requires-Python: >=3.6
License-File: LICENSE
Requires-Dist: torch
Requires-Dist: numpy
Requires-Dist: matplotlib
Requires-Dist: scikit-learn
